seroapi/__init__.py
seroapi/api/__init__.py
seroapi/api/account_management_api.py
seroapi/api/actions_api.py
seroapi/api/origins_management_and_dynamic_access_control_api.py
seroapi/api_client.py
seroapi/api_response.py
seroapi/configuration.py
seroapi/exceptions.py
seroapi/models/__init__.py
seroapi/models/add_origin_request.py
seroapi/models/add_origin_response.py
seroapi/models/details.py
seroapi/models/get_origin_response.py
seroapi/models/list_origins_response.py
seroapi/models/login_request.py
seroapi/models/login_response.py
seroapi/models/origin_model.py
seroapi/models/registration_request.py
seroapi/models/registration_response.py
seroapi/py.typed
seroapi/rest.py
seroapi-0.2.7.dist-info/METADATA
seroapi-0.2.7.dist-info/WHEEL
seroapi-0.2.7.dist-info/RECORD
