Metadata-Version: 2.1
Name: seroapi
Version: 0.2.7
Summary: sero
Home-page: https://github.com/GIT_USER_ID/GIT_REPO_ID
License: MIT
Keywords: OpenAPI,OpenAPI-Generator,sero
Author: clowzed
Author-email: clowzed.work@gmail.com
Requires-Python: >=3.7,<4.0
Classifier: License :: OSI Approved :: MIT License
Classifier: Programming Language :: Python :: 3
Classifier: Programming Language :: Python :: 3.7
Classifier: Programming Language :: Python :: 3.8
Classifier: Programming Language :: Python :: 3.9
Classifier: Programming Language :: Python :: 3.10
Classifier: Programming Language :: Python :: 3.11
Classifier: Programming Language :: Python :: 3.12
Requires-Dist: pydantic (>=2)
Requires-Dist: python-dateutil (>=2.8.2)
Requires-Dist: typing-extensions (>=4.7.1)
Requires-Dist: urllib3 (>=1.25.3)
Project-URL: Repository, https://github.com/GIT_USER_ID/GIT_REPO_ID
